aliyunsdkalikafka/__init__.py
aliyunsdkalikafka/endpoint.py
aliyunsdkalikafka/request/__init__.py
aliyunsdkalikafka/request/v20190916/ChangeResourceGroupRequest.py
aliyunsdkalikafka/request/v20190916/ConvertPostPayOrderRequest.py
aliyunsdkalikafka/request/v20190916/CreateAclRequest.py
aliyunsdkalikafka/request/v20190916/CreateConsumerGroupRequest.py
aliyunsdkalikafka/request/v20190916/CreatePostPayOrderRequest.py
aliyunsdkalikafka/request/v20190916/CreatePrePayOrderRequest.py
aliyunsdkalikafka/request/v20190916/CreateSaslUserRequest.py
aliyunsdkalikafka/request/v20190916/CreateTopicRequest.py
aliyunsdkalikafka/request/v20190916/DeleteAclRequest.py
aliyunsdkalikafka/request/v20190916/DeleteConsumerGroupRequest.py
aliyunsdkalikafka/request/v20190916/DeleteInstanceRequest.py
aliyunsdkalikafka/request/v20190916/DeleteSaslUserRequest.py
aliyunsdkalikafka/request/v20190916/DeleteTopicRequest.py
aliyunsdkalikafka/request/v20190916/DescribeAclsRequest.py
aliyunsdkalikafka/request/v20190916/DescribeSaslUsersRequest.py
aliyunsdkalikafka/request/v20190916/EnableAutoGroupCreationRequest.py
aliyunsdkalikafka/request/v20190916/EnableAutoTopicCreationRequest.py
aliyunsdkalikafka/request/v20190916/GetAllInstanceIdListRequest.py
aliyunsdkalikafka/request/v20190916/GetAllowedIpListRequest.py
aliyunsdkalikafka/request/v20190916/GetConsumerListRequest.py
aliyunsdkalikafka/request/v20190916/GetConsumerProgressRequest.py
aliyunsdkalikafka/request/v20190916/GetInstanceListRequest.py
aliyunsdkalikafka/request/v20190916/GetQuotaTipRequest.py
aliyunsdkalikafka/request/v20190916/GetTopicListRequest.py
aliyunsdkalikafka/request/v20190916/GetTopicStatusRequest.py
aliyunsdkalikafka/request/v20190916/GetTopicSubscribeStatusRequest.py
aliyunsdkalikafka/request/v20190916/ListTagResourcesRequest.py
aliyunsdkalikafka/request/v20190916/ModifyInstanceNameRequest.py
aliyunsdkalikafka/request/v20190916/ModifyPartitionNumRequest.py
aliyunsdkalikafka/request/v20190916/ModifyTopicRemarkRequest.py
aliyun_python_sdk_alikafka-1.0.6.dist-info/LICENSE
aliyun_python_sdk_alikafka-1.0.6.dist-info/METADATA
aliyun_python_sdk_alikafka-1.0.6.dist-info/WHEEL
aliyun_python_sdk_alikafka-1.0.6.dist-info/top_level.txt
aliyun_python_sdk_alikafka-1.0.6.dist-info/RECORD
